m3chat_sdk/__init__.py
m3chat_sdk/client.py
m3chat_sdk/types.py
m3chat_sdk-0.0.1.dist-info/licenses/LICENSE
m3chat_sdk-0.0.1.dist-info/METADATA
m3chat_sdk-0.0.1.dist-info/WHEEL
m3chat_sdk-0.0.1.dist-info/top_level.txt
m3chat_sdk-0.0.1.dist-info/RECORD
