Metadata-Version: 2.4
Name: m3chat_sdk
Version: 0.0.1
Summary: Python SDK for M3 Chat
Home-page: https://github.com/m3-chat/python-sdk
Author: myferr
Author-email: contactme.myfer@protonmail.com
License: Apache-2.0
Classifier: Programming Language :: Python :: 3
Classifier: License :: OSI Approved :: Apache Software License
Requires-Python: >=3.7
License-File: LICENSE
Requires-Dist: requests
Dynamic: license-file
